users/__init__.py
users/apps.py
users/migrations/0001_initial.py
users/migrations/__init__.py
django_empty_users_app-1.0.1.dist-info/LICENSE
django_empty_users_app-1.0.1.dist-info/METADATA
django_empty_users_app-1.0.1.dist-info/WHEEL
django_empty_users_app-1.0.1.dist-info/top_level.txt
django_empty_users_app-1.0.1.dist-info/RECORD
